jupitest/.private
jupitest/LICENSE
jupitest/__init__.py
jupitest/__main__.py
jupitest/hooking/__init__.py
jupitest/hooking/ante_build_hook.py
jupitest/hooking/ante_release_hook.py
jupitest/hooking/post_build_hook.py
jupitest/hooking/post_release_hook.py
jupitest/host/__init__.py
jupitest/host/main_host.py
jupitest/host/reloader.py
jupitest/host/result.py
jupitest/misc/__init__.py
jupitest/misc/builder.py
jupitest/misc/default_shared_data.json
jupitest/misc/my_theme.py
jupitest/pyrustic_data/build_report.json
jupitest/pyrustic_data/hooking.json
jupitest/pyrustic_data/hubstore.json
jupitest/pyrustic_data/release_info.json
jupitest/pyrustic_data/backstage/config/build.json
jupitest/pyrustic_data/backstage/config/init.json
jupitest/pyrustic_data/backstage/config/release.json
jupitest/pyrustic_data/backstage/data/build_report.json
jupitest/pyrustic_data/backstage/data/github_release_form.json
jupitest/pyrustic_data/backstage/hooking/build.json
jupitest/pyrustic_data/backstage/hooking/init.json
jupitest/pyrustic_data/backstage/hooking/release.json
jupitest/pyrustic_data/backstage/report/build_report.json
jupitest/pyrustic_data/backstage/report/release_report.json
jupitest/pyrustic_data/hubstore/img.json
jupitest/pyrustic_data/hubstore/promotion.json
jupitest/view/__init__.py
jupitest/view/log_window.py
jupitest/view/main_view.py
jupitest/view/toolbar.py
jupitest/view/tree_hook.py
secret/SCRATCH.py
secret/__init__.py
tests/__init__.py
tests/__main__.py
jupitest-0.0.14.dist-info/LICENSE
jupitest-0.0.14.dist-info/METADATA
jupitest-0.0.14.dist-info/WHEEL
jupitest-0.0.14.dist-info/entry_points.txt
jupitest-0.0.14.dist-info/top_level.txt
jupitest-0.0.14.dist-info/RECORD
