Metadata-Version: 2.1
Name: jupitest
Version: 0.0.14
Summary: Graphical Test Runner built with Pyrustic
Home-page: https://github.com/pyrustic/jupitest
Author: Pyrustic Evangelist
Author-email: rusticalex@yahoo.com
Maintainer: Pyrustic Evangelist
Maintainer-email: rusticalex@yahoo.com
License: MIT
Keywords: pyrustic,tool,gui,graphical-test-runner,desktop-application,tkinter,tests,test-runner,app
Platform: UNKNOWN
Classifier: Programming Language :: Python :: 3
Classifier: License :: OSI Approved :: MIT License
Classifier: Operating System :: OS Independent
Requires-Python: >=3.5
License-File: LICENSE
Requires-Dist: tkf
